scaffie/__init__.py
scaffie/config.py
scaffie/extensions.py
scaffie/input.py
scaffie/renderer.py
scaffie/template.py
scaffie/utils.py
scaffie-0.1.0.dist-info/METADATA
scaffie-0.1.0.dist-info/WHEEL
scaffie-0.1.0.dist-info/top_level.txt
scaffie-0.1.0.dist-info/RECORD
