Metadata-Version: 2.1
Name: scaffie
Version: 0.1.0
Summary: 내가 쓸려고 만든 패키지
Home-page: https://github.com/clogic/simple-scaffolder
Author: clogic
Author-email: choiseungil29@gmail.com
Classifier: Programming Language :: Python :: 3
Classifier: License :: OSI Approved :: MIT License
Classifier: Operating System :: OS Independent
Requires-Python: >=3.12
